setup.py
inelegant/__init__.py
inelegant/dict.py
inelegant/finder.py
inelegant/fs.py
inelegant/io.py
inelegant/module.py
inelegant/net.py
inelegant/object.py
inelegant/process.py
inelegant/toggle.py
inelegant.egg-info/PKG-INFO
inelegant.egg-info/SOURCES.txt
inelegant.egg-info/dependency_links.txt
inelegant.egg-info/top_level.txt
inelegant/test/__init__.py
inelegant/test/__main__.py
inelegant/test/dict.py
inelegant/test/finder.py
inelegant/test/fs.py
inelegant/test/io.py
inelegant/test/module.py
inelegant/test/net.py
inelegant/test/object.py
inelegant/test/process.py
inelegant/test/toggle.py