Metadata-Version: 1.0
Name: inelegant
Version: 0.3.0
Summary: Inelegant, a directory of weird helpers for tests.
Home-page: https://github.com/confeitaria/inelegant
Author: Adam Victor Brandizzi
Author-email: adam@brandizzi.com.br
License: LGPLv3
Keywords: test,testing
Platform: UNKNOWN
